LICENSE
README.md
setup.py
qute/__init__.py
qute/constants.py
qute/resources.py
qute.egg-info/PKG-INFO
qute.egg-info/SOURCES.txt
qute.egg-info/dependency_links.txt
qute.egg-info/top_level.txt
qute/_res/list_collapsed.png
qute/_res/list_open.png
qute/_res/squares.png
qute/_res/squares_lite.png
qute/extensions/__init__.py
qute/extensions/buttons.py
qute/extensions/dividers.py
qute/extensions/flow_layout.py
qute/extensions/tray.py
qute/extensions/windows.py
qute/styles/space.css
qute/utilities/__init__.py
qute/utilities/_core.py
qute/utilities/derive.py
qute/utilities/designer.py
qute/utilities/events.py
qute/utilities/launch.py
qute/utilities/layouts.py
qute/utilities/menus.py
qute/utilities/pixmaps.py
qute/utilities/request.py
qute/utilities/sizing.py
qute/utilities/styling.py
qute/utilities/widgets.py
qute/utilities/windows.py
qute/vendor/Qt.py
qute/vendor/__init__.py
qute/vendor/scribble/__init__.py
qute/vendor/scribble/core.py