Metadata-Version: 2.1
Name: qute
Version: 4.0.1
Summary: A Qt.py extension which aims to expose additional helper utilities to Qt which are common place within coding projects.
Home-page: https://github.com/mikemalinowski/qute
Author: Mike Malinowski
Author-email: mike.malinowski@outlook.com
Keywords: qute qt pyside pyside2 pyqt
Classifier: Programming Language :: Python
Classifier: License :: OSI Approved :: MIT License
Classifier: Operating System :: OS Independent
License-File: LICENSE
